{
    "machine": "enricher",
    "registryName": "enricher_clump_emerald",
    "recipeTime": 400,
    "requirements": [
        {
            "type": "item",
            "io-type": "input",
            "item": "ore:clumpEmerald",
            "amount": 1
        },
		{
            "type": "item",
            "io-type": "output",
            "item": "ore:dustEnrichedEmerald",
            "amount": 1
        },
		{
            "type": "item",
            "io-type": "output",
            "item": "ore:dustEnrichedEmerald",
            "amount": 1,
			"chance": 0.33
        },
        {
            "type": "energy",
            "io-type": "input",
            "energyPerTick": 256
        },
        {
            "type": "fluid",
            "io-type": "input",
            "fluid": "petrotheum",
            "amount": 100
        }
    ]
}